thecut_durationfield-1.0.7-py2.7-nspkg.pth
thecut/durationfield/forms.py
thecut/durationfield/widgets.py
thecut/durationfield/models.py
thecut/durationfield/__init__.py
thecut/durationfield/utils.py
thecut/durationfield/tests/tests.py
thecut/durationfield/tests/__init__.py
thecut_durationfield-1.0.7.dist-info/WHEEL
thecut_durationfield-1.0.7.dist-info/namespace_packages.txt
thecut_durationfield-1.0.7.dist-info/DESCRIPTION.rst
thecut_durationfield-1.0.7.dist-info/RECORD
thecut_durationfield-1.0.7.dist-info/METADATA
thecut_durationfield-1.0.7.dist-info/metadata.json
thecut_durationfield-1.0.7.dist-info/top_level.txt
