Metadata-Version: 2.0
Name: thecut-durationfield
Version: 1.0.7
Summary: Form and model fields for storing durations on Django modelsas ISO 8601 compliant strings, and returning relativedelta objects.
Home-page: https://github.com/thecut/thecut-durationfield
Author: Josh Crompton
Author-email: josh.crompton@thecut.net.au
License: UNKNOWN
Platform: UNKNOWN
Classifier: Programming Language :: Python
Classifier: Programming Language :: Python :: 2
Classifier: Programming Language :: Python :: 2.6
Classifier: Programming Language :: Python :: 2.7
Classifier: Programming Language :: Python :: 3
Classifier: Programming Language :: Python :: 3.4
Classifier: Development Status :: 5 - Production/Stable
Classifier: Natural Language :: English
Classifier: Environment :: Web Environment
Classifier: Framework :: Django
Classifier: Intended Audience :: Developers
Classifier: License :: OSI Approved :: Apache Software License
Classifier: Operating System :: OS Independent
Classifier: Topic :: Software Development :: Libraries :: Python Modules
Classifier: Topic :: Software Development :: Libraries :: Application Frameworks
Classifier: Topic :: Internet :: WWW/HTTP :: Dynamic Content
Requires-Dist: isodate (>=0.5)
Requires-Dist: python-dateutil (>=2.2)
